autocommitt/__init__.py
autocommitt/cli/__init__.py
autocommitt/cli/main.py
autocommitt/core/__init__.py
autocommitt/core/commit_manager.py
autocommitt/core/ollama_manager.py
autocommitt/tests/__init__.py
autocommitt/utils/__init__.py
autocommitt/utils/check_installation.py
autocommitt/utils/config_manager.py
autocommitt-0.3.0.dist-info/METADATA
autocommitt-0.3.0.dist-info/WHEEL
autocommitt-0.3.0.dist-info/entry_points.txt
autocommitt-0.3.0.dist-info/licenses/LICENSE
autocommitt-0.3.0.dist-info/RECORD
