Metadata-Version: 2.4
Name: autocommitt
Version: 0.3.0
Summary: A CLI tool for generating editable commit messages locally using Ollama.
Author-email: Spartan-71 <anishdabhane71@gmail.com>
License:                                  Apache License
License-File: LICENSE
Keywords: CLI tool,aicommit,autocommit,git automation,local AI
Classifier: Development Status :: 4 - Beta
Classifier: Intended Audience :: Developers
Classifier: Operating System :: MacOS :: MacOS X
Classifier: Operating System :: Microsoft :: Windows
Classifier: Operating System :: POSIX :: Linux
Classifier: Programming Language :: Python :: 3
Requires-Python: >=3.12
Requires-Dist: ollama>=0.4.4
Requires-Dist: platformdirs>=4.3.6
Requires-Dist: psutil>=6.1.1
Requires-Dist: pyreadline3; sys_platform == 'win32'
Requires-Dist: requests>=2.32.3
Requires-Dist: typer>=0.15.1
